{
  "variants": {
    "color=black": { "model": "oak_leaves" },
    "color=blue": { "model": "oak_leaves" },
    "color=brown": { "model": "oak_leaves" },
    "color=cyan": { "model": "oak_leaves" },
    "color=gray": { "model": "oak_leaves" },
    "color=green": { "model": "oak_leaves" },
    "color=light_blue": { "model": "oak_leaves" },
    "color=light_gray": { "model": "oak_leaves" },
    "color=lime": { "model": "oak_leaves" },
    "color=magenta": { "model": "oak_leaves" },
    "color=orange": { "model": "oak_leaves" },
    "color=pink": { "model": "oak_leaves" },
    "color=purple": { "model": "oak_leaves" },
    "color=red": { "model": "oak_leaves" },
    "color=white": { "model": "oak_leaves" },
    "color=yellow": { "model": "oak_leaves" }
  }
}
