{
  "variants": {
    "color=black": {
      "model": "chromaticfoliage:emissive_birch_leaves"
    },
    "color=blue": {
      "model": "chromaticfoliage:emissive_birch_leaves"
    },
    "color=brown": {
      "model": "chromaticfoliage:emissive_birch_leaves"
    },
    "color=cyan": {
      "model": "chromaticfoliage:emissive_birch_leaves"
    },
    "color=gray": {
      "model": "chromaticfoliage:emissive_birch_leaves"
    },
    "color=green": {
      "model": "chromaticfoliage:emissive_birch_leaves"
    },
    "color=light_blue": {
      "model": "chromaticfoliage:emissive_birch_leaves"
    },
    "color=light_gray": {
      "model": "chromaticfoliage:emissive_birch_leaves"
    },
    "color=lime": {
      "model": "chromaticfoliage:emissive_birch_leaves"
    },
    "color=magenta": {
      "model": "chromaticfoliage:emissive_birch_leaves"
    },
    "color=orange": {
      "model": "chromaticfoliage:emissive_birch_leaves"
    },
    "color=pink": {
      "model": "chromaticfoliage:emissive_birch_leaves"
    },
    "color=purple": {
      "model": "chromaticfoliage:emissive_birch_leaves"
    },
    "color=red": {
      "model": "chromaticfoliage:emissive_birch_leaves"
    },
    "color=white": {
      "model": "chromaticfoliage:emissive_birch_leaves"
    },
    "color=yellow": {
      "model": "chromaticfoliage:emissive_birch_leaves"
    }
  }
}
